{
  "random_suffix": "9ed6259eba2b684a",
  "files": {
    "meta": "cm_meta_9ed6259eba2b684a.json",
    "filming": [
      "cm_film_9ed6259eba2b684a_1.json",
      "cm_film_9ed6259eba2b684a_2.json",
      "cm_film_9ed6259eba2b684a_3.json",
      "cm_film_9ed6259eba2b684a_4.json",
      "cm_film_9ed6259eba2b684a_5.json",
      "cm_film_9ed6259eba2b684a_6.json",
      "cm_film_9ed6259eba2b684a_7.json"
    ],
    "represented": [
      "cm_repr_9ed6259eba2b684a_1.json",
      "cm_repr_9ed6259eba2b684a_2.json",
      "cm_repr_9ed6259eba2b684a_3.json"
    ]
  }
}